MANIFEST.in
README.md
setup.py
PloidPy/__init__.py
PloidPy/binom_model.py
PloidPy/nbinom.py
PloidPy/parse_bam.c
PloidPy/parse_bam.h
PloidPy/ploidy_model.py
PloidPy/plot_read_data.py
PloidPy/process_bam.c
PloidPy/process_bam.pxd
PloidPy/process_bam.pyx
PloidPy.egg-info/PKG-INFO
PloidPy.egg-info/SOURCES.txt
PloidPy.egg-info/dependency_links.txt
PloidPy.egg-info/requires.txt
PloidPy.egg-info/top_level.txt
htslib/.appveyor.yml
htslib/.git
htslib/.gitattributes
htslib/.gitignore
htslib/.travis.yml
htslib/INSTALL
htslib/LICENSE
htslib/Makefile
htslib/NEWS
htslib/README
htslib/README.large_positions.md
htslib/README.md
htslib/aclocal.m4
htslib/bcf_sr_sort.c
htslib/bcf_sr_sort.h
htslib/bgzf.c
htslib/bgzip.1
htslib/bgzip.c
htslib/config.mk.in
htslib/configure.ac
htslib/errmod.c
htslib/faidx.5
htslib/faidx.c
htslib/header.c
htslib/header.h
htslib/hfile.c
htslib/hfile_gcs.c
htslib/hfile_internal.h
htslib/hfile_libcurl.c
htslib/hfile_net.c
htslib/hfile_s3.c
htslib/hfile_s3_write.c
htslib/hts.c
htslib/hts_internal.h
htslib/hts_os.c
htslib/htsfile.1
htslib/htsfile.c
htslib/htslib-s3-plugin.7
htslib/htslib.mk
htslib/htslib.pc.in
htslib/htslib_vars.mk
htslib/kfunc.c
htslib/knetfile.c
htslib/kstring.c
htslib/md5.c
htslib/multipart.c
htslib/plugin.c
htslib/probaln.c
htslib/realn.c
htslib/regidx.c
htslib/region.c
htslib/sam.5
htslib/sam.c
htslib/sam_internal.h
htslib/synced_bcf_reader.c
htslib/tabix.1
htslib/tabix.c
htslib/tbx.c
htslib/textutils.c
htslib/textutils_internal.h
htslib/thread_pool.c
htslib/thread_pool_internal.h
htslib/vcf.5
htslib/vcf.c
htslib/vcf_sweep.c
htslib/vcfutils.c
htslib/version.sh
htslib/cram/cram.h
htslib/cram/cram_codecs.c
htslib/cram/cram_codecs.h
htslib/cram/cram_decode.c
htslib/cram/cram_decode.h
htslib/cram/cram_encode.c
htslib/cram/cram_encode.h
htslib/cram/cram_external.c
htslib/cram/cram_index.c
htslib/cram/cram_index.h
htslib/cram/cram_io.c
htslib/cram/cram_io.h
htslib/cram/cram_samtools.c
htslib/cram/cram_samtools.h
htslib/cram/cram_stats.c
htslib/cram/cram_stats.h
htslib/cram/cram_structs.h
htslib/cram/mFILE.c
htslib/cram/mFILE.h
htslib/cram/misc.h
htslib/cram/open_trace_file.c
